{
  "id": "tam_tru",
  "national_code": "1.004194",
  "name": "Đăng ký tạm trú",
  "aliases": [
    "làm tạm trú",
    "đăng ký cư trú tạm thời",
    "khai báo tạm trú"
  ],
  "example_queries": [
    "tôi cần đăng ký tạm trú",
    "chuyển đến chỗ ở mới thì làm tạm trú thế nào",
    "hồ sơ tạm trú cần giấy tờ gì"
  ],
  "negative_keywords": [
    "khai báo tạm vắng",
    "đăng ký thường trú",
    "khai sinh",
    "đăng ký kết hôn",
    "cấp thẻ căn cước"
  ],
  "required_token_groups": [
    ["tạm", "trú"]
  ],
  "agency": "Công an cấp xã",
  "legal_basis": [
    "Luật Cư trú 2020",
    "Nghị định 154/2024/NĐ-CP",
    "Thông tư 75/2022/TT-BTC",
    "Thông tư 53/2025/TT-BCA",
    "Thông tư 54/2025/TT-BCA"
  ],
  "processing_days": 3,
  "fee_vnd": null,
  "clarifying_questions": [
    {
      "key": "khai_thac_duoc_cho_o",
      "text": "Thông tin về chỗ ở hợp pháp của bạn đã có và khai thác được từ cơ sở dữ liệu hoặc VNeID chưa?",
      "answer_type": "boolean"
    },
    {
      "key": "nguoi_chua_thanh_nien",
      "text": "Người đăng ký tạm trú có phải là người chưa thành niên không?",
      "answer_type": "boolean"
    }
  ],
  "requirements": [
    {
      "code": "to_khai_ct01",
      "name": "Tờ khai thay đổi thông tin cư trú (Mẫu CT01 theo Thông tư 53/2025/TT-BCA)",
      "condition": null,
      "original_required": true,
      "copies": 0,
      "accepted_doc_types": ["to_khai_ct01"]
    },
    {
      "code": "chung_minh_cho_o_hop_phap",
      "name": "Giấy tờ, tài liệu chứng minh chỗ ở hợp pháp",
      "condition": "answers.khai_thac_duoc_cho_o == false",
      "condition_label": "Chỉ xuất trình khi hệ thống không khai thác được thông tin về chỗ ở hợp pháp",
      "original_required": true,
      "copies": 0,
      "accepted_doc_types": ["giay_to_cho_o_hop_phap"]
    },
    {
      "code": "y_kien_nguoi_dai_dien",
      "name": "Ý kiến đồng ý của cha, mẹ hoặc người giám hộ trong Tờ khai CT01 hoặc bằng văn bản",
      "condition": "answers.nguoi_chua_thanh_nien == true",
      "condition_label": "Áp dụng khi người đăng ký tạm trú là người chưa thành niên",
      "original_required": true,
      "copies": 0,
      "accepted_doc_types": ["van_ban_dong_y_nguoi_giam_ho"]
    }
  ],
  "form_templates": [
    {
      "id": "CT01-TT-53-2025-BCA-TAM-TRU",
      "name": "Tờ khai thay đổi thông tin cư trú (đăng ký tạm trú)",
      "fields": [
        {"key": "ho_ten", "label": "Họ, chữ đệm và tên", "type": "text", "required": true, "ocr_sources": ["cccd.ho_ten"]},
        {"key": "ngay_sinh", "label": "Ngày, tháng, năm sinh", "type": "date", "required": true, "ocr_sources": ["cccd.ngay_sinh"]},
        {"key": "gioi_tinh", "label": "Giới tính", "type": "select", "required": true, "options": ["Nam", "Nữ"], "ocr_sources": ["cccd.gioi_tinh"]},
        {"key": "so_dinh_danh", "label": "Số định danh cá nhân", "type": "text", "required": true, "ocr_sources": ["cccd.so_cccd"]},
        {"key": "so_dien_thoai", "label": "Số điện thoại liên hệ", "type": "text", "required": false},
        {"key": "dia_chi_tam_tru", "label": "Địa chỉ đề nghị đăng ký tạm trú", "type": "text", "required": true},
        {"key": "thoi_han_tam_tru", "label": "Thời hạn tạm trú đề nghị", "type": "text", "required": true},
        {"key": "ho_ten_chu_ho", "label": "Họ tên chủ hộ (nếu đăng ký vào hộ đã có)", "type": "text", "required": false},
        {"key": "quan_he_voi_chu_ho", "label": "Quan hệ với chủ hộ", "type": "text", "required": false},
        {"key": "y_kien_nguoi_dai_dien", "label": "Ý kiến cha, mẹ hoặc người giám hộ (với người chưa thành niên)", "type": "text", "required": false}
      ]
    }
  ],
  "source_url": "https://thutuc.dichvucong.gov.vn/p/home/dvc-tthc-thu-tuc-hanh-chinh-chi-tiet.html?ma_thu_tuc=5974"
}
